{"styleId":"A4103_244","name":"A4103_244_Bikini Top","program":5795,"programName":"Recycled Seersucker","material":"59%Recycled Polyester 25% Polyamid 16% Elastan","groupId":"drop-swim","colorNames":"Check Azure Blue","colorId":244,"responsible":true,"weight":45950,"sizeRange":"32, 34, 36, 38, 40, 42, 44","chest":0,"waist":0,"hip":0,"bottomWidth":0,"totalLenght":15.5,"inseamLenght":0,"sleeveLenght":0,"height":0,"length":0,"width":0,"heelHeight":0,"wholesalePriceDKK":280,"wholesalePriceEUR":38,"wholesalePriceUSD":57,"wholesalePriceGBP":38,"retailPriceDKK":699,"retailPriceEUR":95,"retailPriceUSD":135,"retailPriceGBP":95,"retailRMB":995,"filters":["rtw14"],"PRODUCT_GROUP":"Bikini Top","assets1":"https://res.cloudinary.com/dd6fpxydm/image/upload/v1628537809/22.1/PACKSHOTS/A4103_5795_244.png","assets2":"https://res.cloudinary.com/dd6fpxydm/image/upload/v1628537809/22.1/PACKSHOTS/A4103_5795_244_1.png","inclusive":true,"re-runner":true,"assets":["https://res.cloudinary.com/dd6fpxydm/image/upload/v1628537809/22.1/PACKSHOTS/A4103_5795_244.png","https://res.cloudinary.com/dd6fpxydm/image/upload/v1628537809/22.1/PACKSHOTS/A4103_5795_244_1.png"]}