{
  "waist": 0,
  "retailPriceUSD": 155,
  "inseamLenght": 0,
  "chest": 0,
  "totalLenght": 0,
  "assets": [
    [
      "https://res.cloudinary.com/dd6fpxydm/image/upload/v1628685902/22.1/PACKSHOTS/A4218_5828_99.png"
    ],
    [
      "https://res.cloudinary.com/dd6fpxydm/image/upload/v1628685917/22.1/PACKSHOTS/A4218_5828_99_3.png"
    ],
    [
      "https://res.cloudinary.com/dd6fpxydm/image/upload/v1628685971/22.1/PACKSHOTS/A4218_5828_99_2.png"
    ]
  ],
  "retailRMB": 1195,
  "program": 5828,
  "colorNames": "Black",
  "sleeveLenght": 0,
  "width": 8.5,
  "length": 12,
  "height": 18,
  "material": "100% Recycled Polyester",
  "re-runner": true,
  "wholesalePriceGBP": 46,
  "heelHeight": 0,
  "name": "A4218_099_Fabric Small Bag",
  "inclusive": true,
  "styleId": "A4218_099",
  "assets1": "https://res.cloudinary.com/dd6fpxydm/image/upload/v1628537809/22.1/PACKSHOTS/A4218_5828_099_1.png",
  "assets2": "https://res.cloudinary.com/dd6fpxydm/image/upload/v1628537809/22.1/PACKSHOTS/A4218_99_1.png",
  "PRODUCT_GROUP": "Fabric Small Bag",
  "retailPriceGBP": 115,
  "programName": "Quilted recycled Tech",
  "hip": 0,
  "assets3": "https://res.cloudinary.com/dd6fpxydm/image/upload/v1628537809/22.1/PACKSHOTS/A4218_099_2.png",
  "responsible": true,
  "wholesalePriceEUR": 50,
  "weight": 44310,
  "wholesalePriceDKK": 360,
  "groupId": "drop-1",
  "wholesalePriceUSD": 65,
  "bottomWidth": 0,
  "filters": [
    "acc1"
  ],
  "sizeRange": "ONE SIZE",
  "retailPriceEUR": 125,
  "retailPriceDKK": 899,
  "colorId": 99
}