{
	"styleId": "F7201_309",
	"name": "F7201_309_Shirt",
	"program": 6479,
	"programName": "Cotton Poplin",
	"material": "100% Organic Cotton",
	"groupId": "drop-2",
	"colorNames": "Orangedotcom",
	"colorId": 309,
	"responsible": true,
	"weight": 49040,
	"sizeRange": "32, 34, 36, 38, 40, 42, 44",
	"chest": 55,
	"waist": 0,
	"hip": 0,
	"bottomWidth": 0,
	"totalLenght": 73,
	"inseamLenght": 0,
	"sleeveLenght": 65,
	"height": 0,
	"length": 0,
	"width": 0,
	"heelHeight": 0,
	"wholesalePriceDKK": 428,
	"wholesalePriceEUR": 63,
	"wholesalePriceUSD": 86,
	"wholesalePriceGBP": 56,
	"retailPriceDKK": 1199,
	"retailPriceEUR": 175,
	"retailPriceUSD": 195,
	"retailPriceGBP": 155,
	"retailRMB": 1595,
	"filters": ["rtw2"],
	"PRODUCT_GROUP": "Shirt",
	"assets1": "https://res.cloudinary.com/dd6fpxydm/image/upload/v1628537809/22.1/PACKSHOTS/F7201_6479_309.png",
	"assets2": "https://res.cloudinary.com/dd6fpxydm/image/upload/v1628537809/22.1/PACKSHOTS/F7201_309_1.png",
	"inclusive": true,
	"re-runner": true,
	"assets": [
		"https://res.cloudinary.com/dd6fpxydm/image/upload/v1628537809/22.1/PACKSHOTS/F7201_6479_309.png",
		"https://res.cloudinary.com/dd6fpxydm/image/upload/v1628537809/22.1/PACKSHOTS/F7201_309_1.png"
	]
}
